CHANGELOG.rst
MANIFEST.in
README.rst
setup.py
echarts_cities_pypkg/__init__.py
echarts_cities_pypkg/_version.py
echarts_cities_pypkg.egg-info/PKG-INFO
echarts_cities_pypkg.egg-info/SOURCES.txt
echarts_cities_pypkg.egg-info/dependency_links.txt
echarts_cities_pypkg.egg-info/not-zip-safe
echarts_cities_pypkg.egg-info/requires.txt
echarts_cities_pypkg.egg-info/top_level.txt
echarts_cities_pypkg/resources/echarts-cities-js/AD.json
echarts_cities_pypkg/resources/echarts-cities-js/AE.json
echarts_cities_pypkg/resources/echarts-cities-js/AF.json
echarts_cities_pypkg/resources/echarts-cities-js/AG.json
echarts_cities_pypkg/resources/echarts-cities-js/AI.json
echarts_cities_pypkg/resources/echarts-cities-js/AL.json
echarts_cities_pypkg/resources/echarts-cities-js/AM.json
echarts_cities_pypkg/resources/echarts-cities-js/AO.json
echarts_cities_pypkg/resources/echarts-cities-js/AQ.json
echarts_cities_pypkg/resources/echarts-cities-js/AR.json
echarts_cities_pypkg/resources/echarts-cities-js/AS.json
echarts_cities_pypkg/resources/echarts-cities-js/AT.json
echarts_cities_pypkg/resources/echarts-cities-js/AU.json
echarts_cities_pypkg/resources/echarts-cities-js/AW.json
echarts_cities_pypkg/resources/echarts-cities-js/AX.json
echarts_cities_pypkg/resources/echarts-cities-js/AZ.json
echarts_cities_pypkg/resources/echarts-cities-js/BA.json
echarts_cities_pypkg/resources/echarts-cities-js/BB.json
echarts_cities_pypkg/resources/echarts-cities-js/BD.json
echarts_cities_pypkg/resources/echarts-cities-js/BE.json
echarts_cities_pypkg/resources/echarts-cities-js/BF.json
echarts_cities_pypkg/resources/echarts-cities-js/BG.json
echarts_cities_pypkg/resources/echarts-cities-js/BH.json
echarts_cities_pypkg/resources/echarts-cities-js/BI.json
echarts_cities_pypkg/resources/echarts-cities-js/BJ.json
echarts_cities_pypkg/resources/echarts-cities-js/BL.json
echarts_cities_pypkg/resources/echarts-cities-js/BM.json
echarts_cities_pypkg/resources/echarts-cities-js/BN.json
echarts_cities_pypkg/resources/echarts-cities-js/BO.json
echarts_cities_pypkg/resources/echarts-cities-js/BQ.json
echarts_cities_pypkg/resources/echarts-cities-js/BR.json
echarts_cities_pypkg/resources/echarts-cities-js/BS.json
echarts_cities_pypkg/resources/echarts-cities-js/BT.json
